Workbook

Sheet Pizza Sales Calculations
A1: OrderNumber | B1: OrderPlace | C1: OrderReady | D1: ItemOrdered1 | E1: ItemOrdered2 | F1: ItemOrdered3 | G1: Delivery | H1: DeliveryZipCode | I1: DeliveryDistance | J1: OrderDelivery | K1: TotalPrice(NoTaxes) | L1: DeliveryDuration | M1: NumberofItemsOrdered | N1: WeightItem1 | O1: WeightItem2 | P1: WeightItem3 | Q1: TotalWeightOrder | R1: CostTraditionalDelivery | S1: DroneRange | T1: DroneDeliveryDuration | U1: CostDroneDelivery | V1: PriceItem1 | W1: PriceItem2 | X1: PriceItem3
A2: 1 | B2: 42370.518 | C2: 42370.528 | D2: Small | E2: Medium | G2: FALSE | H2: 70803 | I2: 0 | J2: 42370.53 | K2: 19.58 | L2: =('Pizza Sales Calculations'!$J2-'Pizza Sales Calculations'!$C2)*24*60 -> 2.9666667 | M2: =COUNTA('Pizza Sales Calculations'!$D2:$F2) -> 2 | R2: =IF('Pizza Sales Calculations'!$G2=TRUE, Parameters!$B$17*'Pizza Sales Calculations'!$L2*2, 0) -> 0
A3: 2 | B3: 42370.523 | C3: 42370.534 | D3: Large | G3: FALSE | H3: 70804 | I3: 0 | J3: 42370.536 | K3: 15.35 | L3: =('Pizza Sales Calculations'!$J3-'Pizza Sales Calculations'!$C3)*24*60 -> 2.9666667 | M3: =COUNTA('Pizza Sales Calculations'!$D3:$F3) -> 1 | R3: =IF('Pizza Sales Calculations'!$G3=TRUE, Parameters!$B$17*'Pizza Sales Calculations'!$L3*2, 0) -> 0
A4: 3 | B4: 42370.527 | C4: 42370.537 | D4: Small | E4: Medium | G4: FALSE | H4: 70804 | I4: 0 | J4: 42370.539 | K4: 19.58 | L4: =('Pizza Sales Calculations'!$J4-'Pizza Sales Calculations'!$C4)*24*60 -> 2.9833333 | M4: =COUNTA('Pizza Sales Calculations'!$D4:$F4) -> 2 | R4: =IF('Pizza Sales Calculations'!$G4=TRUE, Parameters!$B$17*'Pizza Sales Calculations'!$L4*2, 0) -> 0
A5: 4 | B5: 42370.493 | C5: 42370.503 | D5: Small | G5: FALSE | H5: 70806 | I5: 0 | J5: 42370.505 | K5: 7.99 | L5: =('Pizza Sales Calculations'!$J5-'Pizza Sales Calculations'!$C5)*24*60 -> 3 | M5: =COUNTA('Pizza Sales Calculations'!$D5:$F5) -> 1 | R5: =IF('Pizza Sales Calculations'!$G5=TRUE, Parameters!$B$17*'Pizza Sales Calculations'!$L5*2, 0) -> 0
A6: 5 | B6: 42370.451 | C6: 42370.461 | D6: Medium | G6: TRUE | H6: 70805 | I6: 2.4793323 | J6: 42370.47 | K6: 11.59 | L6: =('Pizza Sales Calculations'!$J6-'Pizza Sales Calculations'!$C6)*24*60 -> 12.383333 | M6: =COUNTA('Pizza Sales Calculations'!$D6:$F6) -> 1 | R6: =IF('Pizza Sales Calculations'!$G6=TRUE, Parameters!$B$17*'Pizza Sales Calculations'!$L6*2, 0) -> 3.5086111
A7: 6 | B7: 42370.521 | C7: 42370.532 | D7: Small | G7: TRUE | H7: 70803 | I7: 2.3576023 | J7: 42370.54 | K7: 7.99 | L7: =('Pizza Sales Calculations'!$J7-'Pizza Sales Calculations'!$C7)*24*60 -> 11.783333 | M7: =COUNTA('Pizza Sales Calculations'!$D7:$F7) -> 1 | R7: =IF('Pizza Sales Calculations'!$G7=TRUE, Parameters!$B$17*'Pizza Sales Calculations'!$L7*2, 0) -> 3.3386111
A8: 7 | B8: 42370.523 | C8: 42370.533 | D8: Medium | G8: TRUE | H8: 70807 | I8: 2.0571563 | J8: 42370.541 | K8: 11.59 | L8: =('Pizza Sales Calculations'!$J8-'Pizza Sales Calculations'!$C8)*24*60 -> 10.283333 | M8: =COUNTA('Pizza Sales Calculations'!$D8:$F8) -> 1 | R8: =IF('Pizza Sales Calculations'!$G8=TRUE, Parameters!$B$17*'Pizza Sales Calculations'!$L8*2, 0) -> 2.9136111
A9: 8 | B9: 42370.557 | C9: 42370.568 | D9: Small | E9: Medium | G9: TRUE | H9: 70804 | I9: 4.8175175 | J9: 42370.585 | K9: 19.58 | L9: =('Pizza Sales Calculations'!$J9-'Pizza Sales Calculations'!$C9)*24*60 -> 24.083333 | M9: =COUNTA('Pizza Sales Calculations'!$D9:$F9) -> 2 | R9: =IF('Pizza Sales Calculations'!$G9=TRUE, Parameters!$B$17*'Pizza Sales Calculations'!$L9*2, 0) -> 6.8236111
A10: 9 | B10: 42370.488 | C10: 42370.499 | D10: Small | E10: Medium | G10: TRUE | H10: 70803 | I10: 3.1066756 | J10: 42370.51 | K10: 19.58 | L10: =('Pizza Sales Calculations'!$J10-'Pizza Sales Calculations'!$C10)*24*60 -> 15.533333 | M10: =COUNTA('Pizza Sales Calculations'!$D10:$F10) -> 2 | R10: =IF('Pizza Sales Calculations'!$G10=TRUE, Parameters!$B$17*'Pizza Sales Calculations'!$L10*2, 0) -> 4.4011111
A11: 10 | B11: 42370.435 | C11: 42370.445 | D11: Medium | G11: TRUE | H11: 70804 | I11: 4.556016 | J11: 42370.461 | K11: 11.59 | L11: =('Pizza Sales Calculations'!$J11-'Pizza Sales Calculations'!$C11)*24*60 -> 22.766667 | M11: =COUNTA('Pizza Sales Calculations'!$D11:$F11) -> 1 | R11: =IF('Pizza Sales Calculations'!$G11=TRUE, Parameters!$B$17*'Pizza Sales Calculations'!$L11*2, 0) -> 6.4505556
A12: 11 | B12: 42370.514 | C12: 42370.524 | D12: Medium | G12: FALSE | H12: 70804 | I12: 0 | J12: 42370.526 | K12: 11.59 | L12: =('Pizza Sales Calculations'!$J12-'Pizza Sales Calculations'!$C12)*24*60 -> 3 | M12: =COUNTA('Pizza Sales Calculations'!$D12:$F12) -> 1 | R12: =IF('Pizza Sales Calculations'!$G12=TRUE, Parameters!$B$17*'Pizza Sales Calculations'!$L12*2, 0) -> 0
A13: 12 | B13: 42370.523 | C13: 42370.534 | D13: Small | E13: Large | G13: FALSE | H13: 70805 | I13: 0 | J13: 42370.536 | K13: 23.34 | L13: =('Pizza Sales Calculations'!$J13-'Pizza Sales Calculations'!$C13)*24*60 -> 2.9833333 | M13: =COUNTA('Pizza Sales Calculations'!$D13:$F13) -> 2 | R13: =IF('Pizza Sales Calculations'!$G13=TRUE, Parameters!$B$17*'Pizza Sales Calculations'!$L13*2, 0) -> 0
A14: 13 | B14: 42370.482 | C14: 42370.493 | D14: Small | E14: Medium | G14: TRUE | H14: 70806 | I14: 3.1092624 | J14: 42370.504 | K14: 19.58 | L14: =('Pizza Sales Calculations'!$J14-'Pizza Sales Calculations'!$C14)*24*60 -> 15.533333 | M14: =COUNTA('Pizza Sales Calculations'!$D14:$F14) -> 2 | R14: =IF('Pizza Sales Calculations'!$G14=TRUE, Parameters!$B$17*'Pizza Sales Calculations'!$L14*2, 0) -> 4.4011111
A15: 14 | B15: 42370.51 | C15: 42370.521 | D15: Small | G15: FALSE | H15: 70804 | I15: 0 | J15: 42370.523 | K15: 7.99 | L15: =('Pizza Sales Calculations'!$J15-'Pizza Sales Calculations'!$C15)*24*60 -> 3 | M15: =COUNTA('Pizza Sales Calculations'!$D15:$F15) -> 1 | R15: =IF('Pizza Sales Calculations'!$G15=TRUE, Parameters!$B$17*'Pizza Sales Calculations'!$L15*2, 0) -> 0
A16: 15 | B16: 42370.529 | C16: 42370.539 | D16: Medium | G16: FALSE | H16: 70803 | I16: 0 | J16: 42370.541 | K16: 11.59 | L16: =('Pizza Sales Calculations'!$J16-'Pizza Sales Calculations'!$C16)*24*60 -> 2.9833333 | M16: =COUNTA('Pizza Sales Calculations'!$D16:$F16) -> 1 | R16: =IF('Pizza Sales Calculations'!$G16=TRUE, Parameters!$B$17*'Pizza Sales Calculations'!$L16*2, 0) -> 0
A17: 16 | B17: 42370.497 | C17: 42370.507 | D17: Small | E17: Medium | G17: TRUE | H17: 70806 | I17: 3.4135037 | J17: 42370.519 | K17: 19.58 | L17: =('Pizza Sales Calculations'!$J17-'Pizza Sales Calculations'!$C17)*24*60 -> 17.066667 | M17: =COUNTA('Pizza Sales Calculations'!$D17:$F17) -> 2 | R17: =IF('Pizza Sales Calculations'!$G17=TRUE, Parameters!$B$17*'Pizza Sales Calculations'!$L17*2, 0) -> 4.8355556
A18: 17 | B18: 42370.576 | C18: 42370.586 | D18: Medium | G18: TRUE | H18: 70806 | I18: 2.5641446 | J18: 42370.595 | K18: 11.59 | L18: =('Pizza Sales Calculations'!$J18-'Pizza Sales Calculations'!$C18)*24*60 -> 12.816667 | M18: =COUNTA('Pizza Sales Calculations'!$D18:$F18) -> 1 | R18: =IF('Pizza Sales Calculations'!$G18=TRUE, Parameters!$B$17*'Pizza Sales Calculations'!$L18*2, 0) -> 3.6313889
A19: 18 | B19: 42370.52 | C19: 42370.53 | D19: Medium | G19: TRUE | H19: 70803 | I19: 4.4542172 | J19: 42370.546 | K19: 11.59 | L19: =('Pizza Sales Calculations'!$J19-'Pizza Sales Calculations'!$C19)*24*60 -> 22.266667 | M19: =COUNTA('Pizza Sales Calculations'!$D19:$F19) -> 1 | R19: =IF('Pizza Sales Calculations'!$G19=TRUE, Parameters!$B$17*'Pizza Sales Calculations'!$L19*2, 0) -> 6.3088889
A20: 19 | B20: 42370.531 | C20: 42370.542 | D20: Large | G20: TRUE | H20: 70803 | I20: 4.1472808 | J20: 42370.556 | K20: 15.35 | L20: =('Pizza Sales Calculations'!$J20-'Pizza Sales Calculations'!$C20)*24*60 -> 20.733333 | M20: =COUNTA('Pizza Sales Calculations'!$D20:$F20) -> 1 | R20: =IF('Pizza Sales Calculations'!$G20=TRUE, Parameters!$B$17*'Pizza Sales Calculations'!$L20*2, 0) -> 5.8744444
A21: 20 | B21: 42370.494 | C21: 42370.505 | D21: Large | G21: FALSE | H21: 70807 | I21: 0 | J21: 42370.507 | K21: 15.35 | L21: =('Pizza Sales Calculations'!$J21-'Pizza Sales Calculations'!$C21)*24*60 -> 3.0166667 | M21: =COUNTA('Pizza Sales Calculations'!$D21:$F21) -> 1 | R21: =IF('Pizza Sales Calculations'!$G21=TRUE, Parameters!$B$17*'Pizza Sales Calculations'!$L21*2, 0) -> 0
A22: 21 | B22: 42370.431 | C22: 42370.441 | D22: Medium | G22: TRUE | H22: 70804 | I22: 2.0976294 | J22: 42370.448 | K22: 11.59 | L22: =('Pizza Sales Calculations'!$J22-'Pizza Sales Calculations'!$C22)*24*60 -> 10.483333 | M22: =COUNTA('Pizza Sales Calculations'!$D22:$F22) -> 1 | R22: =IF('Pizza Sales Calculations'!$G22=TRUE, Parameters!$B$17*'Pizza Sales Calculations'!$L22*2, 0) -> 2.9702778
A23: 22 | B23: 42370.426 | C23: 42370.436 | D23: Small | G23: FALSE | H23: 70805 | I23: 0 | J23: 42370.438 | K23: 7.99 | L23: =('Pizza Sales Calculations'!$J23-'Pizza Sales Calculations'!$C23)*24*60 -> 3.0166667 | M23: =COUNTA('Pizza Sales Calculations'!$D23:$F23) -> 1 | R23: =IF('Pizza Sales Calculations'!$G23=TRUE, Parameters!$B$17*'Pizza Sales Calculations'!$L23*2, 0) -> 0
A24: 23 | B24: 42370.528 | C24: 42370.539 | D24: Large | G24: TRUE | H24: 70805 | I24: 2.5751773 | J24: 42370.548 | K24: 15.35 | L24: =('Pizza Sales Calculations'!$J24-'Pizza Sales Calculations'!$C24)*24*60 -> 12.866667 | M24: =COUNTA('Pizza Sales Calculations'!$D24:$F24) -> 1 | R24: =IF('Pizza Sales Calculations'!$G24=TRUE, Parameters!$B$17*'Pizza Sales Calculations'!$L24*2, 0) -> 3.6455556
A25: 24 | B25: 42370.525 | C25: 42370.536 | D25: Medium | G25: TRUE | H25: 70804 | I25: 4.1683095 | J25: 42370.55 | K25: 11.59 | L25: =('Pizza Sales Calculations'!$J25-'Pizza Sales Calculations'!$C25)*24*60 -> 20.833333 | M25: =COUNTA('Pizza Sales Calculations'!$D25:$F25) -> 1 | R25: =IF('Pizza Sales Calculations'!$G25=TRUE, Parameters!$B$17*'Pizza Sales Calculations'!$L25*2, 0) -> 5.9027778
A26: 25 | B26: 42370.439 | C26: 42370.449 | D26: Medium | E26: Large | G26: TRUE | H26: 70804 | I26: 1.9678453 | J26: 42370.456 | K26: 25.94 | L26: =('Pizza Sales Calculations'!$J26-'Pizza Sales Calculations'!$C26)*24*60 -> 9.8333333 | M26: =COUNTA('Pizza Sales Calculations'!$D26:$F26) -> 2 | R26: =IF('Pizza Sales Calculations'!$G26=TRUE, Parameters!$B$17*'Pizza Sales Calculations'!$L26*2, 0) -> 2.7861111
A27: 26 | B27: 42370.471 | C27: 42370.482 | D27: Small | E27: Large | G27: FALSE | H27: 70807 | I27: 0 | J27: 42370.484 | K27: 23.34 | L27: =('Pizza Sales Calculations'!$J27-'Pizza Sales Calculations'!$C27)*24*60 -> 2.9666667 | M27: =COUNTA('Pizza Sales Calculations'!$D27:$F27) -> 2 | R27: =IF('Pizza Sales Calculations'!$G27=TRUE, Parameters!$B$17*'Pizza Sales Calculations'!$L27*2, 0) -> 0
A28: 27 | B28: 42371.523 | C28: 42371.533 | D28: Small | E28: Medium | G28: TRUE | H28: 70806 | I28: 3.6126489 | J28: 42371.546 | K28: 19.58 | L28: =('Pizza Sales Calculations'!$J28-'Pizza Sales Calculations'!$C28)*24*60 -> 18.05 | M28: =COUNTA('Pizza Sales Calculations'!$D28:$F28) -> 2 | R28: =IF('Pizza Sales Calculations'!$G28=TRUE, Parameters!$B$17*'Pizza Sales Calculations'!$L28*2, 0) -> 5.1141667
A29: 28 | B29: 42371.508 | C29: 42371.519 | D29: Small | G29: FALSE | H29: 70803 | I29: 0 | J29: 42371.521 | K29: 7.99 | L29: =('Pizza Sales Calculations'!$J29-'Pizza Sales Calculations'!$C29)*24*60 -> 3 | M29: =COUNTA('Pizza Sales Calculations'!$D29:$F29) -> 1 | R29: =IF('Pizza Sales Calculations'!$G29=TRUE, Parameters!$B$17*'Pizza Sales Calculations'!$L29*2, 0) -> 0
A30: 29 | B30: 42371.459 | C30: 42371.469 | D30: Large | G30: FALSE | H30: 70805 | I30: 0 | J30: 42371.471 | K30: 15.35 | L30: =('Pizza Sales Calculations'!$J30-'Pizza Sales Calculations'!$C30)*24*60 -> 2.9833333 | M30: =COUNTA('Pizza Sales Calculations'!$D30:$F30) -> 1 | R30: =IF('Pizza Sales Calculations'!$G30=TRUE, Parameters!$B$17*'Pizza Sales Calculations'!$L30*2, 0) -> 0
A31: 30 | B31: 42371.549 | C31: 42371.559 | D31: Medium | G31: TRUE | H31: 70805 | I31: 2.9869999 | J31: 42371.57 | K31: 11.59 | L31: =('Pizza Sales Calculations'!$J31-'Pizza Sales Calculations'!$C31)*24*60 -> 14.933333 | M31: =COUNTA('Pizza Sales Calculations'!$D31:$F31) -> 1 | R31: =IF('Pizza Sales Calculations'!$G31=TRUE, Parameters!$B$17*'Pizza Sales Calculations'!$L31*2, 0) -> 4.2311111
A32: 31 | B32: 42371.513 | C32: 42371.523 | D32: Large | G32: FALSE | H32: 70804 | I32: 0 | J32: 42371.525 | K32: 15.35 | L32: =('Pizza Sales Calculations'!$J32-'Pizza Sales Calculations'!$C32)*24*60 -> 2.95 | M32: =COUNTA('Pizza Sales Calculations'!$D32:$F32) -> 1 | R32: =IF('Pizza Sales Calculations'!$G32=TRUE, Parameters!$B$17*'Pizza Sales Calculations'!$L32*2, 0) -> 0
A33: 32 | B33: 42371.523 | C33: 42371.534 | D33: Medium | G33: TRUE | H33: 70805 | I33: 1.8750196 | J33: 42371.54 | K33: 11.59 | L33: =('Pizza Sales Calculations'!$J33-'Pizza Sales Calculations'!$C33)*24*60 -> 9.3666667 | M33: =COUNTA('Pizza Sales Calculations'!$D33:$F33) -> 1 | R33: =IF('Pizza Sales Calculations'!$G33=TRUE, Parameters!$B$17*'Pizza Sales Calculations'!$L33*2, 0) -> 2.6538889
A34: 33 | B34: 42371.431 | C34: 42371.442 | D34: Large | G34: FALSE | H34: 70804 | I34: 0 | J34: 42371.444 | K34: 15.35 | L34: =('Pizza Sales Calculations'!$J34-'Pizza Sales Calculations'!$C34)*24*60 -> 2.9833333 | M34: =COUNTA('Pizza Sales Calculations'!$D34:$F34) -> 1 | R34: =IF('Pizza Sales Calculations'!$G34=TRUE, Parameters!$B$17*'Pizza Sales Calculations'!$L34*2, 0) -> 0
A35: 34 | B35: 42371.466 | C35: 42371.477 | D35: Small | E35: Medium | G35: TRUE | H35: 70803 | I35: 2.6679713 | J35: 42371.486 | K35: 19.58 | L35: =('Pizza Sales Calculations'!$J35-'Pizza Sales Calculations'!$C35)*24*60 -> 13.333333 | M35: =COUNTA('Pizza Sales Calculations'!$D35:$F35) -> 2 | R35: =IF('Pizza Sales Calculations'!$G35=TRUE, Parameters!$B$17*'Pizza Sales Calculations'!$L35*2, 0) -> 3.7777778
A36: 35 | B36: 42371.537 | C36: 42371.548 | D36: Medium | G36: FALSE | H36: 70806 | I36: 0 | J36: 42371.55 | K36: 11.59 | L36: =('Pizza Sales Calculations'!$J36-'Pizza Sales Calculations'!$C36)*24*60 -> 2.9833333 | M36: =COUNTA('Pizza Sales Calculations'!$D36:$F36) -> 1 | R36: =IF('Pizza Sales Calculations'!$G36=TRUE, Parameters!$B$17*'Pizza Sales Calculations'!$L36*2, 0) -> 0
A37: 36 | B37: 42371.48 | C37: 42371.49 | D37: Large | G37: TRUE | H37: 70805 | I37: 3.9470079 | J37: 42371.504 | K37: 15.35 | L37: =('Pizza Sales Calculations'!$J37-'Pizza Sales Calculations'!$C37)*24*60 -> 19.733333 | M37: =COUNTA('Pizza Sales Calculations'!$D37:$F37) -> 1 | R37: =IF('Pizza Sales Calculations'!$G37=TRUE, Parameters!$B$17*'Pizza Sales Calculations'!$L37*2, 0) -> 5.5911111
A38: 37 | B38: 42371.54 | C38: 42371.55 | D38: Small | G38: TRUE | H38: 70805 | I38: 2.2604541 | J38: 42371.558 | K38: 7.99 | L38: =('Pizza Sales Calculations'!$J38-'Pizza Sales Calculations'!$C38)*24*60 -> 11.3 | M38: =COUNTA('Pizza Sales Calculations'!$D38:$F38) -> 1 | R38: =IF('Pizza Sales Calculations'!$G38=TRUE, Parameters!$B$17*'Pizza Sales Calculations'!$L38*2, 0) -> 3.2016667
A39: 38 | B39: 42371.466 | C39: 42371.477 | D39: Medium | G39: TRUE | H39: 70807 | I39: 3.8581374 | J39: 42371.49 | K39: 11.59 | L39: =('Pizza Sales Calculations'!$J39-'Pizza Sales Calculations'!$C39)*24*60 -> 19.283333 | M39: =COUNTA('Pizza Sales Calculations'!$D39:$F39) -> 1 | R39: =IF('Pizza Sales Calculations'!$G39=TRUE, Parameters!$B$17*'Pizza Sales Calculations'!$L39*2, 0) -> 5.4636111
A40: 39 | B40: 42371.514 | C40: 42371.525 | D40: Large | G40: TRUE | H40: 70805 | I40: 2.3749016 | J40: 42371.533 | K40: 15.35 | L40: =('Pizza Sales Calculations'!$J40-'Pizza Sales Calculations'!$C40)*24*60 -> 11.866667 | M40: =COUNTA('Pizza Sales Calculations'!$D40:$F40) -> 1 | R40: =IF('Pizza Sales Calculations'!$G40=TRUE, Parameters!$B$17*'Pizza Sales Calculations'!$L40*2, 0) -> 3.3622222
A41: 40 | B41: 42371.472 | C41: 42371.483 | D41: Small | E41: Large | G41: TRUE | H41: 70805 | I41: 2.8217374 | J41: 42371.492 | K41: 23.34 | L41: =('Pizza Sales Calculations'!$J41-'Pizza Sales Calculations'!$C41)*24*60 -> 14.1 | M41: =COUNTA('Pizza Sales Calculations'!$D41:$F41) -> 2 | R41: =IF('Pizza Sales Calculations'!$G41=TRUE, Parameters!$B$17*'Pizza Sales Calculations'!$L41*2, 0) -> 3.995
A42: 41 | B42: 42371.467 | C42: 42371.477 | D42: Medium | G42: TRUE | H42: 70803 | I42: 3.2253941 | J42: 42371.488 | K42: 11.59 | L42: =('Pizza Sales Calculations'!$J42-'Pizza Sales Calculations'!$C42)*24*60 -> 16.116667 | M42: =COUNTA('Pizza Sales Calculations'!$D42:$F42) -> 1 | R42: =IF('Pizza Sales Calculations'!$G42=TRUE, Parameters!$B$17*'Pizza Sales Calculations'!$L42*2, 0) -> 4.5663889
A43: 42 | B43: 42371.542 | C43: 42371.552 | D43: Small | G43: TRUE | H43: 70807 | I43: 1.8333816 | J43: 42371.558 | K43: 7.99 | L43: =('Pizza Sales Calculations'!$J43-'Pizza Sales Calculations'!$C43)*24*60 -> 9.1666667 | M43: =COUNTA('Pizza Sales Calculations'!$D43:$F43) -> 1 | R43: =IF('Pizza Sales Calculations'!$G43=TRUE, Parameters!$B$17*'Pizza Sales Calculations'!$L43*2, 0) -> 2.5972222
A44: 43 | B44: 42371.468 | C44: 42371.479 | D44: Small | E44: Medium | G44: TRUE | H44: 70804 | I44: 2.1957366 | J44: 42371.486 | K44: 19.58 | L44: =('Pizza Sales Calculations'!$J44-'Pizza Sales Calculations'!$C44)*24*60 -> 10.966667 | M44: =COUNTA('Pizza Sales Calculations'!$D44:$F44) -> 2 | R44: =IF('Pizza Sales Calculations'!$G44=TRUE, Parameters!$B$17*'Pizza Sales Calculations'!$L44*2, 0) -> 3.1072222
A45: 44 | B45: 42371.474 | C45: 42371.484 | D45: Medium | G45: TRUE | H45: 70803 | I45: 2.0345866 | J45: 42371.491 | K45: 11.59 | L45: =('Pizza Sales Calculations'!$J45-'Pizza Sales Calculations'!$C45)*24*60 -> 10.166667 | M45: =COUNTA('Pizza Sales Calculations'!$D45:$F45) -> 1 | R45: =IF('Pizza Sales Calculations'!$G45=TRUE, Parameters!$B$17*'Pizza Sales Calculations'!$L45*2, 0) -> 2.8805556
A46: 45 | B46: 42371.49 | C46: 42371.5 | D46: Large | G46: TRUE | H46: 70806 | I46: 3.2053034 | J46: 42371.511 | K46: 15.35 | L46: =('Pizza Sales Calculations'!$J46-'Pizza Sales Calculations'!$C46)*24*60 -> 16.016667 | M46: =COUNTA('Pizza Sales Calculations'!$D46:$F46) -> 1 | R46: =IF('Pizza Sales Calculations'!$G46=TRUE, Parameters!$B$17*'Pizza Sales Calculations'!$L46*2, 0) -> 4.5380556
A47: 46 | B47: 42371.459 | C47: 42371.47 | D47: Large | G47: FALSE | H47: 70806 | I47: 0 | J47: 42371.472 | K47: 15.35 | L47: =('Pizza Sales Calculations'!$J47-'Pizza Sales Calculations'!$C47)*24*60 -> 3 | M47: =COUNTA('Pizza Sales Calculations'!$D47:$F47) -> 1 | R47: =IF('Pizza Sales Calculations'!$G47=TRUE, Parameters!$B$17*'Pizza Sales Calculations'!$L47*2, 0) -> 0
A48: 47 | B48: 42371.529 | C48: 42371.539 | D48: Large | G48: FALSE | H48: 70805 | I48: 0 | J48: 42371.541 | K48: 15.35 | L48: =('Pizza Sales Calculations'!$J48-'Pizza Sales Calculations'!$C48)*24*60 -> 2.9666667 | M48: =COUNTA('Pizza Sales Calculations'!$D48:$F48) -> 1 | R48: =IF('Pizza Sales Calculations'!$G48=TRUE, Parameters!$B$17*'Pizza Sales Calculations'!$L48*2, 0) -> 0
A49: 48 | B49: 42371.466 | C49: 42371.477 | D49: Medium | G49: TRUE | H49: 70806 | I49: 2.7278589 | J49: 42371.486 | K49: 11.59 | L49: =('Pizza Sales Calculations'!$J49-'Pizza Sales Calculations'!$C49)*24*60 -> 13.633333 | M49: =COUNTA('Pizza Sales Calculations'!$D49:$F49) -> 1 | R49: =IF('Pizza Sales Calculations'!$G49=TRUE, Parameters!$B$17*'Pizza Sales Calculations'!$L49*2, 0) -> 3.8627778
A50: 49 | B50: 42371.58 | C50: 42371.591 | D50: Medium | G50: FALSE | H50: 70804 | I50: 0 | J50: 42371.593 | K50: 11.59 | L50: =('Pizza Sales Calculations'!$J50-'Pizza Sales Calculations'!$C50)*24*60 -> 2.9833333 | M50: =COUNTA('Pizza Sales Calculations'!$D50:$F50) -> 1 | R50: =IF('Pizza Sales Calculations'!$G50=TRUE, Parameters!$B$17*'Pizza Sales Calculations'!$L50*2, 0) -> 0
A51: 50 | B51: 42371.572 | C51: 42371.582 | D51: Medium | G51: TRUE | H51: 70804 | I51: 2.9843168 | J51: 42371.592 | K51: 11.59 | L51: =('Pizza Sales Calculations'!$J51-'Pizza Sales Calculations'!$C51)*24*60 -> 14.916667 | M51: =COUNTA('Pizza Sales Calculations'!$D51:$F51) -> 1 | R51: =IF('Pizza Sales Calculations'!$G51=TRUE, Parameters!$B$17*'Pizza Sales Calculations'!$L51*2, 0) -> 4.2263889
A52: 51 | B52: 42371.469 | C52: 42371.479 | D52: Medium | E52: Large | G52: TRUE | H52: 70805 | I52: 3.1715636 | J52: 42371.49 | K52: 25.94 | L52: =('Pizza Sales Calculations'!$J52-'Pizza Sales Calculations'!$C52)*24*60 -> 15.85 | M52: =COUNTA('Pizza Sales Calculations'!$D52:$F52) -> 2 | R52: =IF('Pizza Sales Calculations'!$G52=TRUE, Parameters!$B$17*'Pizza Sales Calculations'!$L52*2, 0) -> 4.4908333
A53: 52 | B53: 42371.503 | C53: 42371.514 | D53: Large | G53: TRUE | H53: 70805 | I53: 4.0929926 | J53: 42371.528 | K53: 15.35 | L53: =('Pizza Sales Calculations'!$J53-'Pizza Sales Calculations'!$C53)*24*60 -> 20.45 | M53: =COUNTA('Pizza Sales Calculations'!$D53:$F53) -> 1 | R53: =IF('Pizza Sales Calculations'!$G53=TRUE, Parameters!$B$17*'Pizza Sales Calculations'!$L53*2, 0) -> 5.7941667
A54: 53 | B54: 42371.437 | C54: 42371.447 | D54: Small | E54: Medium | G54: FALSE | H54: 70803 | I54: 0 | J54: 42371.449 | K54: 19.58 | L54: =('Pizza Sales Calculations'!$J54-'Pizza Sales Calculations'!$C54)*24*60 -> 3.0166667 | M54: =COUNTA('Pizza Sales Calculations'!$D54:$F54) -> 2 | R54: =IF('Pizza Sales Calculations'!$G54=TRUE, Parameters!$B$17*'Pizza Sales Calculations'!$L54*2, 0) -> 0
A55: 54 | B55: 42371.482 | C55: 42371.493 | D55: Large | G55: TRUE | H55: 70804 | I55: 2.910333 | J55: 42371.503 | K55: 15.35 | L55: =('Pizza Sales Calculations'!$J55-'Pizza Sales Calculations'!$C55)*24*60 -> 14.55 | M55: =COUNTA('Pizza Sales Calculations'!$D55:$F55) -> 1 | R55: =IF('Pizza Sales Calculations'!$G55=TRUE, Parameters!$B$17*'Pizza Sales Calculations'!$L55*2, 0) -> 4.1225
A56: 55 | B56: 42371.495 | C56: 42371.506 | D56: Medium | G56: TRUE | H56: 70804 | I56: 1.1108594 | J56: 42371.51 | K56: 11.59 | L56: =('Pizza Sales Calculations'!$J56-'Pizza Sales Calculations'!$C56)*24*60 -> 5.55 | M56: =COUNTA('Pizza Sales Calculations'!$D56:$F56) -> 1 | R56: =IF('Pizza Sales Calculations'!$G56=TRUE, Parameters!$B$17*'Pizza Sales Calculations'!$L56*2, 0) -> 1.5725
A57: 56 | B57: 42371.523 | C57: 42371.534 | D57: Large | G57: FALSE | H57: 70806 | I57: 0 | J57: 42371.536 | K57: 15.35 | L57: =('Pizza Sales Calculations'!$J57-'Pizza Sales Calculations'!$C57)*24*60 -> 2.9833333 | M57: =COUNTA('Pizza Sales Calculations'!$D57:$F57) -> 1 | R57: =IF('Pizza Sales Calculations'!$G57=TRUE, Parameters!$B$17*'Pizza Sales Calculations'!$L57*2, 0) -> 0
A58: 57 | B58: 42371.516 | C58: 42371.526 | D58: Small | E58: Medium | G58: FALSE | H58: 70806 | I58: 0 | J58: 42371.528 | K58: 19.58 | L58: =('Pizza Sales Calculations'!$J58-'Pizza Sales Calculations'!$C58)*24*60 -> 2.9833333 | M58: =COUNTA('Pizza Sales Calculations'!$D58:$F58) -> 2 | R58: =IF('Pizza Sales Calculations'!$G58=TRUE, Parameters!$B$17*'Pizza Sales Calculations'!$L58*2, 0) -> 0
A59: 58 | B59: 42371.477 | C59: 42371.487 | D59: Large | G59: FALSE | H59: 70805 | I59: 0 | J59: 42371.489 | K59: 15.35 | L59: =('Pizza Sales Calculations'!$J59-'Pizza Sales Calculations'!$C59)*24*60 -> 3 | M59: =COUNTA('Pizza Sales Calculations'!$D59:$F59) -> 1 | R59: =IF('Pizza Sales Calculations'!$G59=TRUE, Parameters!$B$17*'Pizza Sales Calculations'!$L59*2, 0) -> 0
A60: 59 | B60: 42371.471 | C60: 42371.482 | D60: Small | E60: Medium | G60: TRUE | H60: 70804 | I60: 3.1454837 | J60: 42371.493 | K60: 19.58 | L60: =('Pizza Sales Calculations'!$J60-'Pizza Sales Calculations'!$C60)*24*60 -> 15.716667 | M60: =COUNTA('Pizza Sales Calculations'!$D60:$F60) -> 2 | R60: =IF('Pizza Sales Calculations'!$G60=TRUE, Parameters!$B$17*'Pizza Sales Calculations'!$L60*2, 0) -> 4.4530556
A61: 60 | B61: 42371.458 | C61: 42371.469 | D61: Medium | G61: TRUE | H61: 70807 | I61: 3.1618977 | J61: 42371.479 | K61: 11.59 | L61: =('Pizza Sales Calculations'!$J61-'Pizza Sales Calculations'!$C61)*24*60 -> 15.8 | M61: =COUNTA('Pizza Sales Calculations'!$D61:$F61) -> 1 | R61: =IF('Pizza Sales Calculations'!$G61=TRUE, Parameters!$B$17*'Pizza Sales Calculations'!$L61*2, 0) -> 4.4766667
A62: 61 | B62: 42371.489 | C62: 42371.5 | D62: Small | G62: FALSE | H62: 70804 | I62: 0 | J62: 42371.502 | K62: 7.99 | L62: =('Pizza Sales Calculations'!$J62-'Pizza Sales Calculations'!$C62)*24*60 -> 2.9833333 | M62: =COUNTA('Pizza Sales Calculations'!$D62:$F62) -> 1 | R62: =IF('Pizza Sales Calculations'!$G62=TRUE, Parameters!$B$17*'Pizza Sales Calculations'!$L62*2, 0) -> 0
A63: 62 | B63: 42371.539 | C63: 42371.549 | D63: Medium | G63: TRUE | H63: 70804 | I63: 2.0121791 | J63: 42371.556 | K63: 11.59 | L63: =('Pizza Sales Calculations'!$J63-'Pizza Sales Calculations'!$C63)*24*60 -> 10.05 | M63: =COUNTA('Pizza Sales Calculations'!$D63:$F63) -> 1 | R63: =IF('Pizza Sales Calculations'!$G63=TRUE, Parameters!$B$17*'Pizza Sales Calculations'!$L63*2, 0) -> 2.8475
A64: 63 | B64: 42371.492 | C64: 42371.503 | D64: Small | E64: Medium | G64: TRUE | H64: 70808 | I64: 4.9794773 | J64: 42371.52 | K64: 19.58 | L64: =('Pizza Sales Calculations'!$J64-'Pizza Sales Calculations'!$C64)*24*60 -> 24.883333 | M64: =COUNTA('Pizza Sales Calculations'!$D64:$F64) -> 2 | R64: =IF('Pizza Sales Calculations'!$G64=TRUE, Parameters!$B$17*'Pizza Sales Calculations'!$L64*2, 0) -> 7.0502778
A65: 64 | B65: 42371.433 | C65: 42371.443 | D65: Large | G65: TRUE | H65: 70804 | I65: 4.4351197 | J65: 42371.459 | K65: 15.35 | L65: =('Pizza Sales Calculations'!$J65-'Pizza Sales Calculations'!$C65)*24*60 -> 22.166667 | M65: =COUNTA('Pizza Sales Calculations'!$D65:$F65) -> 1 | R65: =IF('Pizza Sales Calculations'!$G65=TRUE, Parameters!$B$17*'Pizza Sales Calculations'!$L65*2, 0) -> 6.2805556
A66: 65 | B66: 42371.522 | C66: 42371.532 | D66: Small | E66: Medium | G66: FALSE | H66: 70805 | I66: 0 | J66: 42371.535 | K66: 19.58 | L66: =('Pizza Sales Calculations'!$J66-'Pizza Sales Calculations'!$C66)*24*60 -> 3 | M66: =COUNTA('Pizza Sales Calculations'!$D66:$F66) -> 2 | R66: =IF('Pizza Sales Calculations'!$G66=TRUE, Parameters!$B$17*'Pizza Sales Calculations'!$L66*2, 0) -> 0
A67: 66 | B67: 42371.609 | C67: 42371.619 | D67: Large | G67: FALSE | H67: 70804 | I67: 0 | J67: 42371.621 | K67: 15.35 | L67: =('Pizza Sales Calculations'!$J67-'Pizza Sales Calculations'!$C67)*24*60 -> 3 | M67: =COUNTA('Pizza Sales Calculations'!$D67:$F67) -> 1 | R67: =IF('Pizza Sales Calculations'!$G67=TRUE, Parameters!$B$17*'Pizza Sales Calculations'!$L67*2, 0) -> 0
A68: 67 | B68: 42371.55 | C68: 42371.56 | D68: Large | G68: FALSE | H68: 70807 | I68: 0 | J68: 42371.562 | K68: 15.35 | L68: =('Pizza Sales Calculations'!$J68-'Pizza Sales Calculations'!$C68)*24*60 -> 2.9833333 | M68: =COUNTA('Pizza Sales Calculations'!$D68:$F68) -> 1 | R68: =IF('Pizza Sales Calculations'!$G68=TRUE, Parameters!$B$17*'Pizza Sales Calculations'!$L68*2, 0) -> 0
A69: 68 | B69: 42371.577 | C69: 42371.588 | D69: Small | E69: Medium | G69: TRUE | H69: 70805 | I69: 4.1676381 | J69: 42371.602 | K69: 19.58 | L69: =('Pizza Sales Calculations'!$J69-'Pizza Sales Calculations'!$C69)*24*60 -> 20.833333 | M69: =COUNTA('Pizza Sales Calculations'!$D69:$F69) -> 2 | R69: =IF('Pizza Sales Calculations'!$G69=TRUE, Parameters!$B$17*'Pizza Sales Calculations'!$L69*2, 0) -> 5.9027778
A70: 69 | B70: 42371.461 | C70: 42371.472 | D70: Large | G70: TRUE | H70: 70805 | I70: 3.9637534 | J70: 42371.486 | K70: 15.35 | L70: =('Pizza Sales Calculations'!$J70-'Pizza Sales Calculations'!$C70)*24*60 -> 19.816667 | M70: =COUNTA('Pizza Sales Calculations'!$D70:$F70) -> 1 | R70: =IF('Pizza Sales Calculations'!$G70=TRUE, Parameters!$B$17*'Pizza Sales Calculations'!$L70*2, 0) -> 5.6147222
A71: 70 | B71: 42371.439 | C71: 42371.45 | D71: Small | E71: Medium | G71: FALSE | H71: 70805 | I71: 0 | J71: 42371.452 | K71: 19.58 | L71: =('Pizza Sales Calculations'!$J71-'Pizza Sales Calculations'!$C71)*24*60 -> 2.9666667 | M71: =COUNTA('Pizza Sales Calculations'!$D71:$F71) -> 2 | R71: =IF('Pizza Sales Calculations'!$G71=TRUE, Parameters!$B$17*'Pizza Sales Calculations'!$L71*2, 0) -> 0
A72: 71 | B72: 42371.525 | C72: 42371.536 | D72: Medium | E72: Large | G72: FALSE | H72: 70804 | I72: 0 | J72: 42371.538 | K72: 25.94 | L72: =('Pizza Sales Calculations'!$J72-'Pizza Sales Calculations'!$C72)*24*60 -> 2.9666667 | M72: =COUNTA('Pizza Sales Calculations'!$D72:$F72) -> 2 | R72: =IF('Pizza Sales Calculations'!$G72=TRUE, Parameters!$B$17*'Pizza Sales Calculations'!$L72*2, 0) -> 0
A73: 72 | B73: 42371.52 | C73: 42371.531 | D73: Small | E73: Medium | G73: FALSE | H73: 70804 | I73: 0 | J73: 42371.533 | K73: 19.58 | L73: =('Pizza Sales Calculations'!$J73-'Pizza Sales Calculations'!$C73)*24*60 -> 2.9666667 | M73: =COUNTA('Pizza Sales Calculations'!$D73:$F73) -> 2 | R73: =IF('Pizza Sales Calculations'!$G73=TRUE, Parameters!$B$17*'Pizza Sales Calculations'!$L73*2, 0) -> 0
A74: 73 | B74: 42371.51 | C74: 42371.521 | D74: Small | G74: FALSE | H74: 70805 | I74: 0 | J74: 42371.523 | K74: 7.99 | L74: =('Pizza Sales Calculations'!$J74-'Pizza Sales Calculations'!$C74)*24*60 -> 3 | M74: =COUNTA('Pizza Sales Calculations'!$D74:$F74) -> 1 | R74: =IF('Pizza Sales Calculations'!$G74=TRUE, Parameters!$B$17*'Pizza Sales Calculations'!$L74*2, 0) -> 0
A75: 74 | B75: 42371.508 | C75: 42371.518 | D75: Large | G75: TRUE | H75: 70806 | I75: 5.2816256 | J75: 42371.536 | K75: 15.35 | L75: =('Pizza Sales Calculations'!$J75-'Pizza Sales Calculations'!$C75)*24*60 -> 26.4 | M75: =COUNTA('Pizza Sales Calculations'!$D75:$F75) -> 1 | R75: =IF('Pizza Sales Calculations'!$G75=TRUE, Parameters!$B$17*'Pizza Sales Calculations'!$L75*2, 0) -> 7.48
A76: 75 | B76: 42371.433 | C76: 42371.443 | D76: Large | G76: FALSE | H76: 70804 | I76: 0 | J76: 42371.445 | K76: 15.35 | L76: =('Pizza Sales Calculations'!$J76-'Pizza Sales Calculations'!$C76)*24*60 -> 2.9833333 | M76: =COUNTA('Pizza Sales Calculations'!$D76:$F76) -> 1 | R76: =IF('Pizza Sales Calculations'!$G76=TRUE, Parameters!$B$17*'Pizza Sales Calculations'!$L76*2, 0) -> 0
A77: 76 | B77: 42371.517 | C77: 42371.527 | D77: Large | G77: FALSE | H77: 70805 | I77: 0 | J77: 42371.529 | K77: 15.35 | L77: =('Pizza Sales Calculations'!$J77-'Pizza Sales Calculations'!$C77)*24*60 -> 2.9833333 | M77: =COUNTA('Pizza Sales Calculations'!$D77:$F77) -> 1 | R77: =IF('Pizza Sales Calculations'!$G77=TRUE, Parameters!$B$17*'Pizza Sales Calculations'!$L77*2, 0) -> 0
A78: 77 | B78: 42371.478 | C78: 42371.489 | D78: Small | G78: TRUE | H78: 70804 | I78: 3.2452103 | J78: 42371.5 | K78: 7.99 | L78: =('Pizza Sales Calculations'!$J78-'Pizza Sales Calculations'!$C78)*24*60 -> 16.216667 | M78: =COUNTA('Pizza Sales Calculations'!$D78:$F78) -> 1 | R78: =IF('Pizza Sales Calculations'!$G78=TRUE, Parameters!$B$17*'Pizza Sales Calculations'!$L78*2, 0) -> 4.5947222
A79: 78 | B79: 42371.44 | C79: 42371.451 | D79: Medium | G79: TRUE | H79: 70805 | I79: 3.6901531 | J79: 42371.463 | K79: 11.59 | L79: =('Pizza Sales Calculations'!$J79-'Pizza Sales Calculations'!$C79)*24*60 -> 18.45 | M79: =COUNTA('Pizza Sales Calculations'!$D79:$F79) -> 1 | R79: =IF('Pizza Sales Calculations'!$G79=TRUE, Parameters!$B$17*'Pizza Sales Calculations'!$L79*2, 0) -> 5.2275
A80: 79 | B80: 42371.516 | C80: 42371.526 | D80: Small | G80: TRUE | H80: 70804 | I80: 4.2130092 | J80: 42371.541 | K80: 7.99 | L80: =('Pizza Sales Calculations'!$J80-'Pizza Sales Calculations'!$C80)*24*60 -> 21.05 | M80: =COUNTA('Pizza Sales Calculations'!$D80:$F80) -> 1 | R80: =IF('Pizza Sales Calculations'!$G80=TRUE, Parameters!$B$17*'Pizza Sales Calculations'!$L80*2, 0) -> 5.9641667
A81: 80 | B81: 42371.587 | C81: 42371.598 | D81: Large | G81: FALSE | H81: 70805 | I81: 0 | J81: 42371.6 | K81: 15.35 | L81: =('Pizza Sales Calculations'!$J81-'Pizza Sales Calculations'!$C81)*24*60 -> 3 | M81: =COUNTA('Pizza Sales Calculations'!$D81:$F81) -> 1 | R81: =IF('Pizza Sales Calculations'!$G81=TRUE, Parameters!$B$17*'Pizza Sales Calculations'!$L81*2, 0) -> 0
A82: 81 | B82: 42371.47 | C82: 42371.48 | D82: Small | E82: Large | G82: TRUE | H82: 70803 | I82: 2.9900452 | J82: 42371.491 | K82: 23.34 | L82: =('Pizza Sales Calculations'!$J82-'Pizza Sales Calculations'!$C82)*24*60 -> 14.95 | M82: =COUNTA('Pizza Sales Calculations'!$D82:$F82) -> 2 | R82: =IF('Pizza Sales Calculations'!$G82=TRUE, Parameters!$B$17*'Pizza Sales Calculations'!$L82*2, 0) -> 4.2358333
A83: 82 | B83: 42371.489 | C83: 42371.5 | D83: Small | E83: Large | G83: TRUE | H83: 70804 | I83: 1.6619899 | J83: 42371.505 | K83: 23.34 | L83: =('Pizza Sales Calculations'!$J83-'Pizza Sales Calculations'!$C83)*24*60 -> 8.3 | M83: =COUNTA('Pizza Sales Calculations'!$D83:$F83) -> 2 | R83: =IF('Pizza Sales Calculations'!$G83=TRUE, Parameters!$B$17*'Pizza Sales Calculations'!$L83*2, 0) -> 2.3516667
A84: 83 | B84: 42371.478 | C84: 42371.489 | D84: Small | G84: TRUE | H84: 70805 | I84: 3.6148077 | J84: 42371.501 | K84: 7.99 | L84: =('Pizza Sales Calculations'!$J84-'Pizza Sales Calculations'!$C84)*24*60 -> 18.066667 | M84: =COUNTA('Pizza Sales Calculations'!$D84:$F84) -> 1 | R84: =IF('Pizza Sales Calculations'!$G84=TRUE, Parameters!$B$17*'Pizza Sales Calculations'!$L84*2, 0) -> 5.1188889
A85: 84 | B85: 42371.487 | C85: 42371.498 | D85: Large | G85: FALSE | H85: 70805 | I85: 0 | J85: 42371.5 | K85: 15.35 | L85: =('Pizza Sales Calculations'!$J85-'Pizza Sales Calculations'!$C85)*24*60 -> 2.9833333 | M85: =COUNTA('Pizza Sales Calculations'!$D85:$F85) -> 1 | R85: =IF('Pizza Sales Calculations'!$G85=TRUE, Parameters!$B$17*'Pizza Sales Calculations'!$L85*2, 0) -> 0
A86: 85 | B86: 42371.5 | C86: 42371.511 | D86: Medium | G86: FALSE | H86: 70804 | I86: 0 | J86: 42371.513 | K86: 11.59 | L86: =('Pizza Sales Calculations'!$J86-'Pizza Sales Calculations'!$C86)*24*60 -> 3.0166667 | M86: =COUNTA('Pizza Sales Calculations'!$D86:$F86) -> 1 | R86: =IF('Pizza Sales Calculations'!$G86=TRUE, Parameters!$B$17*'Pizza Sales Calculations'!$L86*2, 0) -> 0
A87: 86 | B87: 42371.524 | C87: 42371.535 | D87: Small | G87: TRUE | H87: 70806 | I87: 1.6360924 | J87: 42371.541 | K87: 7.99 | L87: =('Pizza Sales Calculations'!$J87-'Pizza Sales Calculations'!$C87)*24*60 -> 8.1666667 | M87: =COUNTA('Pizza Sales Calculations'!$D87:$F87) -> 1 | R87: =IF('Pizza Sales Calculations'!$G87=TRUE, Parameters!$B$17*'Pizza Sales Calculations'!$L87*2, 0) -> 2.3138889
A88: 87 | B88: 42371.441 | C88: 42371.451 | D88: Small | G88: FALSE | H88: 70803 | I88: 0 | J88: 42371.454 | K88: 7.99 | L88: =('Pizza Sales Calculations'!$J88-'Pizza Sales Calculations'!$C88)*24*60 -> 3 | M88: =COUNTA('Pizza Sales Calculations'!$D88:$F88) -> 1 | R88: =IF('Pizza Sales Calculations'!$G88=TRUE, Parameters!$B$17*'Pizza Sales Calculations'!$L88*2, 0) -> 0
A89: 88 | B89: 42371.517 | C89: 42371.527 | D89: Large | G89: TRUE | H89: 70803 | I89: 2.611567 | J89: 42371.537 | K89: 15.35 | L89: =('Pizza Sales Calculations'!$J89-'Pizza Sales Calculations'!$C89)*24*60 -> 13.05 | M89: =COUNTA('Pizza Sales Calculations'!$D89:$F89) -> 1 | R89: =IF('Pizza Sales Calculations'!$G89=TRUE, Parameters!$B$17*'Pizza Sales Calculations'!$L89*2, 0) -> 3.6975
A90: 89 | B90: 42371.535 | C90: 42371.546 | D90: Large | G90: FALSE | H90: 70804 | I90: 0 | J90: 42371.548 | K90: 15.35 | L90: =('Pizza Sales Calculations'!$J90-'Pizza Sales Calculations'!$C90)*24*60 -> 2.9833333 | M90: =COUNTA('Pizza Sales Calculations'!$D90:$F90) -> 1 | R90: =IF('Pizza Sales Calculations'!$G90=TRUE, Parameters!$B$17*'Pizza Sales Calculations'!$L90*2, 0) -> 0
A91: 90 | B91: 42371.523 | C91: 42371.533 | D91: Large | G91: TRUE | H91: 70806 | I91: 3.8017957 | J91: 42371.546 | K91: 15.35 | L91: =('Pizza Sales Calculations'!$J91-'Pizza Sales Calculations'!$C91)*24*60 -> 19 | M91: =COUNTA('Pizza Sales Calculations'!$D91:$F91) -> 1 | R91: =IF('Pizza Sales Calculations'!$G91=TRUE, Parameters!$B$17*'Pizza Sales Calculations'!$L91*2, 0) -> 5.3833333
A92: 91 | B92: 42371.53 | C92: 42371.54 | D92: Medium | G92: FALSE | H92: 70803 | I92: 0 | J92: 42371.542 | K92: 11.59 | L92: =('Pizza Sales Calculations'!$J92-'Pizza Sales Calculations'!$C92)*24*60 -> 2.9666667 | M92: =COUNTA('Pizza Sales Calculations'!$D92:$F92) -> 1 | R92: =IF('Pizza Sales Calculations'!$G92=TRUE, Parameters!$B$17*'Pizza Sales Calculations'!$L92*2, 0) -> 0
A93: 92 | B93: 42371.521 | C93: 42371.531 | D93: Medium | G93: FALSE | H93: 70805 | I93: 0 | J93: 42371.534 | K93: 11.59 | L93: =('Pizza Sales Calculations'!$J93-'Pizza Sales Calculations'!$C93)*24*60 -> 3.0166667 | M93: =COUNTA('Pizza Sales Calculations'!$D93:$F93) -> 1 | R93: =IF('Pizza Sales Calculations'!$G93=TRUE, Parameters!$B$17*'Pizza Sales Calculations'!$L93*2, 0) -> 0
A94: 93 | B94: 42371.52 | C94: 42371.531 | D94: Small | E94: Large | G94: TRUE | H94: 70805 | I94: 1.9446467 | J94: 42371.537 | K94: 23.34 | L94: =('Pizza Sales Calculations'!$J94-'Pizza Sales Calculations'!$C94)*24*60 -> 9.7166667 | M94: =COUNTA('Pizza Sales Calculations'!$D94:$F94) -> 2 | R94: =IF('Pizza Sales Calculations'!$G94=TRUE, Parameters!$B$17*'Pizza Sales Calculations'!$L94*2, 0) -> 2.7530556
A95: 94 | B95: 42371.505 | C95: 42371.516 | D95: Medium | E95: Large | G95: TRUE | H95: 70803 | I95: 4.3030531 | J95: 42371.531 | K95: 25.94 | L95: =('Pizza Sales Calculations'!$J95-'Pizza Sales Calculations'!$C95)*24*60 -> 21.5 | M95: =COUNTA('Pizza Sales Calculations'!$D95:$F95) -> 2 | R95: =IF('Pizza Sales Calculations'!$G95=TRUE, Parameters!$B$17*'Pizza Sales Calculations'!$L95*2, 0) -> 6.0916667
A96: 95 | B96: 42371.506 | C96: 42371.516 | D96: Large | G96: TRUE | H96: 70805 | I96: 1.275558 | J96: 42371.521 | K96: 15.35 | L96: =('Pizza Sales Calculations'!$J96-'Pizza Sales Calculations'!$C96)*24*60 -> 6.3666667 | M96: =COUNTA('Pizza Sales Calculations'!$D96:$F96) -> 1 | R96: =IF('Pizza Sales Calculations'!$G96=TRUE, Parameters!$B$17*'Pizza Sales Calculations'!$L96*2, 0) -> 1.8038889
A97: 96 | B97: 42371.435 | C97: 42371.446 | D97: Small | E97: Medium | G97: FALSE | H97: 70805 | I97: 0 | J97: 42371.448 | K97: 19.58 | L97: =('Pizza Sales Calculations'!$J97-'Pizza Sales Calculations'!$C97)*24*60 -> 3 | M97: =COUNTA('Pizza Sales Calculations'!$D97:$F97) -> 2 | R97: =IF('Pizza Sales Calculations'!$G97=TRUE, Parameters!$B$17*'Pizza Sales Calculations'!$L97*2, 0) -> 0
A98: 97 | B98: 42371.572 | C98: 42371.582 | D98: Small | G98: TRUE | H98: 70805 | I98: 1.9521653 | J98: 42371.589 | K98: 7.99 | L98: =('Pizza Sales Calculations'!$J98-'Pizza Sales Calculations'!$C98)*24*60 -> 9.75 | M98: =COUNTA('Pizza Sales Calculations'!$D98:$F98) -> 1 | R98: =IF('Pizza Sales Calculations'!$G98=TRUE, Parameters!$B$17*'Pizza Sales Calculations'!$L98*2, 0) -> 2.7625
A99: 98 | B99: 42371.541 | C99: 42371.552 | D99: Small | E99: Large | G99: TRUE | H99: 70806 | I99: 1.5111623 | J99: 42371.557 | K99: 23.34 | L99: =('Pizza Sales Calculations'!$J99-'Pizza Sales Calculations'!$C99)*24*60 -> 7.55 | M99: =COUNTA('Pizza Sales Calculations'!$D99:$F99) -> 2 | R99: =IF('Pizza Sales Calculations'!$G99=TRUE, Parameters!$B$17*'Pizza Sales Calculations'!$L99*2, 0) -> 2.1391667
A100: 99 | B100: 42371.464 | C100: 42371.475 | D100: Medium | G100: FALSE | H100: 70803 | I100: 0 | J100: 42371.477 | K100: 11.59 | L100: =('Pizza Sales Calculations'!$J100-'Pizza Sales Calculations'!$C100)*24*60 -> 3 | M100: =COUNTA('Pizza Sales Calculations'!$D100:$F100) -> 1 | R100: =IF('Pizza Sales Calculations'!$G100=TRUE, Parameters!$B$17*'Pizza Sales Calculations'!$L100*2, 0) -> 0
...

Sheet Parameters
A2: Pizza size | B2: Avg Price | C2: Avg Weight (lbs)
A3: Small | B3: 7 | C3: 1
A4: Medium | B4: 10 | C4: 1.7
A5: Large | B5: 14 | C5: 2.3
A7: Working hours per day | B7: 6
A8: Avg distance delivery for drone elegible deliveries
A9: Drone elegible number of deliveries
A10: Years drone depreciation | B10: 3
A13: Traditional delivery economics | B13: (http://www.pizzatoday.com/departments/back-office/cost-of-delivery/)
A14: Hourly wage (considering SS, Medicare) | B14: =7+1 -> 8
A15: Non-Owned auto insurance and meals / h | B15: 0.5
A16: Delivery cost charged to customer | B16: 2
A17: Cost per minute | B17: =(B14+B15)/60 -> 0.14166667
A20: Drone Characteristics | B20: (http://drones.specout.com/l/1125/DJI-Matrice-600-Pro-M600-Pro) | H20: Alternative (http://drones.specout.com/l/111/Yuneec-Flying-Eyes-HX3)
A21: Operating range (miles) | B21: 3.2
A22: Flight time autonomy (min) | B22: 32
A23: Payload capacity (pounds) | B23: 13.23
A24: Max speed (mph) | B24: 38
A25: Avg speed (mph) | B25: 30
A26: Price | B26: 5000
A27: Maintenance per year | B27: 500
A29: Average time to deliver drone / h | B29: =(B8*2)/B25 -> 0
A30: Maximum drone deliveries per hour | B30: =1/B29 -> #DIV/0!
A33: Pizza drone
A34: Hourly wage drone operator | B34: 10
A35: Number of drones per operator | B35: 12
A36: Electricity per minute | B36: =0.05/60 -> 0.00083333333
A38: Cost per minute operator + electricity | B38: =((B34/B35)/60)+B36 -> 0.014722222
A39: Cost drone per minute | B39: =((B26/3)+B27)/365/B7/60 -> 0.016489092
A40: Total cost drone per minute | B40: =B38+B39 -> 0.031211314
A42: Average orders per day | B42: 100
A43: % Total order elegible for drone delivery
A44: Avg cost traditional delivery (drone eligible)
A45: Avg cost drone delivery
